{"identifiers":{"anidb":"144","tvdb":"71361"},"names":["Inuyasha"],"parameters":{"default_season":"1"},"seasons":{"0":{"episodes":{"1":{"mappings":[{"number":"0"}]}}},"1":{"mappings":[{"end":27,"offset":0,"season":"1","start":1},{"end":54,"offset":-27,"season":"2","start":28},{"end":81,"offset":-54,"season":"3","start":55},{"end":99,"offset":-81,"season":"4","start":82},{"end":126,"offset":-99,"season":"5","start":100},{"end":159,"offset":-126,"season":"6","start":127},{"end":167,"offset":-159,"season":"7","start":160}]}}}