{
    "identifiers": {
        "anidb": "2138",
        "tvdb": "71863"
    },
    "names": [
        "Lupin Sansei: Otakara Henkyaku Daisakusen!!"
    ],
    "parameters": {
        "default_season": "0"
    },
    "seasons": {
        "1": {
            "episodes": {
                "1": {
                    "mappings": [
                        {
                            "number": "25",
                            "season": "0"
                        }
                    ]
                }
            }
        }
    }
}