{"seasons":{"1":{"episodes":{"15":{"mappings":[{"number":"16"}]},"14":{"mappings":[{"number":"15"}]},"17":{"mappings":[{"number":"19"}]},"16":{"mappings":[{"number":"17"}]},"19":{"mappings":[{"number":"23"}]},"18":{"mappings":[{"number":"20"}]},"22":{"mappings":[{"number":"26"}]},"20":{"mappings":[{"number":"24"}]},"21":{"mappings":[{"number":"25"}]}}},"0":{"episodes":{"1":{"mappings":[{"season":"1","number":"14"}]},"3":{"mappings":[{"season":"1","number":"21"}]},"2":{"mappings":[{"season":"1","number":"18"}]},"4":{"mappings":[{"season":"1","number":"22"}]}}}},"identifiers":{"tvdb":"80357","anidb":"2706"},"names":["Anime 80 Nichikan Sekai Isshuu"],"parameters":{"default_season":"1"}}