{
    "identifiers": {
        "anidb": "5444",
        "tvdb": "72454"
    },
    "names": [
        "Meitantei Conan: Agasa-sensei no Chousenjou! Agasa vs Conan & Shounen Tanteidan"
    ],
    "parameters": {
        "default_season": "0"
    },
    "seasons": {
        "1": {
            "episodes": {
                "1": {
                    "mappings": [
                        {
                            "number": "17",
                            "season": "0"
                        }
                    ]
                }
            }
        }
    }
}