{"identifiers":{"anidb":"56","tvdb":"73532"},"names":["Tennis no Ouji-sama"],"parameters":{"default_season":"1"},"seasons":{"0":{"episodes":{"3":{"mappings":[{"number":"0"}]}}},"1":{"mappings":[{"end":26,"offset":0,"season":"1","start":1},{"end":53,"offset":-26,"season":"2","start":27},{"end":75,"offset":-53,"season":"3","start":54},{"end":101,"offset":-75,"season":"4","start":76},{"end":128,"offset":-101,"season":"5","start":102},{"end":165,"offset":-128,"season":"6","start":129},{"end":178,"offset":-165,"season":"7","start":166}]}}}