{"seasons":{"1":{"episodes":{"11":{"mappings":[{"season":"15","number":"35"}]},"10":{"mappings":[{"season":"15","number":"34"}]},"13":{"mappings":[{"season":"15","number":"37"}]},"12":{"mappings":[{"season":"15","number":"36"}]},"14":{"mappings":[{"season":"15","number":"38"}]},"1":{"mappings":[{"season":"15","number":"25"}]},"3":{"mappings":[{"season":"15","number":"27"}]},"2":{"mappings":[{"season":"15","number":"26"}]},"5":{"mappings":[{"season":"15","number":"29"}]},"4":{"mappings":[{"season":"15","number":"28"}]},"7":{"mappings":[{"season":"15","number":"31"}]},"6":{"mappings":[{"season":"15","number":"30"}]},"9":{"mappings":[{"season":"15","number":"33"}]},"8":{"mappings":[{"season":"15","number":"32"}]}}}},"identifiers":{"tvdb":"76703","anidb":"9653"},"names":["Pocket Monsters: Best Wishes! Season 2 - Episode N"],"parameters":{"default_season":"15"}}