{"seasons":{"1":{"identifiers":{"anidb":"522"},"names":["Juusenki L-Gaim"]},"0":{"episodes":{"3":{"identifiers":{"anidb":"2489"},"mappings":[{"season":"1","number":"1"}],"names":["Heavy Metal L-Gaim III: Fullmetal Soldier"]},"2":{"identifiers":{"anidb":"2488"},"mappings":[{"season":"1","number":"1"}],"names":["Heavy Metal L-Gaim II: Farewell My Lovely + Pentagona Dolls"]}},"identifiers":{"anidb":"523"},"names":["Heavy Metal L-Gaim I: Pentagona Window + Lady Gavlet"]}},"identifiers":{"tvdb":"103691"}}