{"33":{"1":{"1":{"1":"5548"},"2":["Sore Ike! Anpanman"]},"0":{"49":{"25":{"17":{"1":"7753"},"18":["Sore Ike! Anpanman: Anpanman to Tanoshii Nakama-tachi"],"49":[{"1":"1","2":"1"}]},"12":{"17":{"1":"7754"},"18":["Anpanman to Yukai na Nakama-tachi"],"49":[{"1":"1","2":"1"}]},"21":{"17":{"1":"7749"},"18":["Sore Ike! Anpanman: Bokura wa Hero"],"49":[{"1":"1","2":"1"}]},"17":{"17":{"1":"7755"},"18":["Anpanman to Happy Otanjoubi"],"49":[{"1":"1","2":"1"}]},"23":{"17":{"1":"7752"},"18":["Sore Ike! Anpanman: Anpanman to Okashi na Nakama"],"49":[{"1":"1","2":"1"}]},"46":{"17":{"1":"7397"},"18":["Sore Ike! Anpanman: Dadandan to Futago no Hoshi"],"49":[{"1":"1","2":"1"}]},"47":{"17":{"1":"7497"},"18":["Sore Ike! Anpanman: Black Nose to Mahou no Uta"],"49":[{"1":"1","2":"1"}]},"45":{"17":{"1":"7740"},"18":["Baikinman tai Baikinman!?"],"49":[{"1":"1","2":"1"}]},"51":{"17":{"1":"9014"},"18":["Sore Ike! Anpanman: Yomigaere Bananajima"],"49":[{"1":"1","2":"1"}]},"50":{"17":{"1":"8330"},"18":["Utatte Teasobi! Anpanman to Mori no Takara"],"49":[{"1":"1","2":"1"}]},"52":{"17":{"1":"9498"},"18":["Sore Ike! Anpanman: Outa to Teasobi Tanoshii ne"],"49":[{"1":"1","2":"1"}]},"19":{"17":{"1":"7748"},"18":["Baikinman to 3-bai Punch"],"49":[{"1":"1","2":"1"}]},"49":{"17":{"1":"8329"},"18":["Sore Ike! Anpanman Sukue! Kokorin to Kiseki no Hoshi"],"49":[{"1":"1","2":"1"}]},"8":{"17":{"1":"7396"},"18":["Sore Ike! Anpanman: Baikinman no Gyakushuu"],"49":[{"1":"1","2":"1"}]}},"2":["Kuroyuki-hime to Motemote Baikinman","Sore Ike! Anpanman: Inochi no Hoshi no Dolly","Sore Ike! Anpanman: Ningyohime no Namida","Sore Ike! Anpanman: Otanjoubi Series","Sore Ike! Anpanman: Tobe! Tobe! Chibigon","Sore Ike! Anpanman: Omusubiman","Sore Ike! Anpanman: Happy no Daibouken","Sore Ike! Anpanman: Kyouryuu Nosshi no Daibouken","Yakisobapanman to Black Sabotenman","Sore Ike! Anpanman: Lyrical Magical Mahou no Gakkou","Sore Yuke! Gedou Otometai","Sore Ike! Anpanman: Kirakiraboshi no Namida","Sore Ike! Anpanman: Keito no Shiro no Christmas","Sore Ike! Anpanman: Yuuki to Honoo to Christmas","Sore Ike! Anpanman: Tenohira o Taiyou ni","Sore Ike! Anpanman: Kieta Jam Ojisan","Minna Atsumare! Anpanman World","Sore Ike! Anpanman: Yousei Rinrin no Himitsu","Sore Ike! Anpanman: Tsumikijou no Himitsu","Tekka no Maki-chan to Kin no Kamameshidon","Sore Ike! Anpanman: Ruby no Negai","Sore Ike! Anpanman: Soratobu Ehon to Glass no Kutsu","Sore Ike! Anpanman: Yuureisen o Yattsukero!!","Tsukiko to Shiratama: Tokimeki Dancing","Sore Ike! Anpanman: Gomira no Hoshi","Dokin-chan no Dokidoki Calendar","Hiya Hiya Hiyariko to Babu Babu Baikinman","Sore Ike! Anpanman: Roll to Laura Ukigumojou no Himitsu","Sore Ike! Anpanman: Kaiketsu Naganegiman to Yakisoba Panman","Sore Ike! Anpanman: Kaiketsu Naganegiman to Doremi-hime","Sore Ike! Anpanman: Shabondama no Purun","Sore Ike! Anpanman: Niji no Pyramid","Sore Ike! Anpanman: Yuuki no Hana ga Hiraku Toki","Kokin-chan to Aoi Namida","Sore Ike! Anpanman: Yumeneko no Kuni no Nyanii","Horrorman to Hora Horako","Sore Ike! Anpanman: Minami no Umi o Sukue!"],"1":{"1":["2841","7761","7751","7742","7743","7739","7559","7558","7759","7758","7553","7552","7551","7550","7557","7750","7555","7554","7392","7757","7562","7560","7561","7737","7556","7548","7549","7741","7746","7747","7744","7745","7760","5812","6078","6079","7547"]}}},"~":1,"1":{"3":"167921"}}