{
    "identifiers": {
        "tvdb": "70668"
    },
    "seasons": {
        "0": {
            "episodes": {
                "1": {
                    "identifiers": {
                        "anidb": "513"
                    },
                    "mappings": [
                        {
                            "season": "1"
                        },
                        {
                            "number": "2",
                            "season": "1"
                        },
                        {
                            "number": "3",
                            "season": "1"
                        }
                    ],
                    "names": [
                        "Gekijouban Cardcaptor Sakura"
                    ]
                },
                "2": {
                    "identifiers": {
                        "anidb": "514"
                    },
                    "mappings": [
                        {
                            "number": "1",
                            "season": "1"
                        },
                        {
                            "season": "1"
                        },
                        {
                            "number": "3",
                            "season": "1"
                        }
                    ],
                    "names": [
                        "Gekijouban Cardcaptor Sakura: Fuuin Sareta Card"
                    ]
                },
                "3": {
                    "identifiers": {
                        "anidb": "102"
                    },
                    "mappings": [
                        {
                            "number": "1"
                        }
                    ],
                    "names": [
                        "Cardcaptor Sakura"
                    ]
                },
                "4": {
                    "identifiers": {
                        "anidb": "102"
                    },
                    "mappings": [
                        {
                            "number": "2"
                        }
                    ],
                    "names": [
                        "Cardcaptor Sakura"
                    ]
                },
                "5": {
                    "identifiers": {
                        "anidb": "102"
                    },
                    "mappings": [
                        {
                            "number": "3"
                        }
                    ],
                    "names": [
                        "Cardcaptor Sakura"
                    ]
                },
                "6": {
                    "identifiers": {
                        "anidb": "102"
                    },
                    "mappings": [
                        {
                            "number": "4"
                        },
                        {
                            "number": "5"
                        },
                        {
                            "number": "7"
                        },
                        {
                            "number": "8"
                        },
                        {
                            "number": "9"
                        },
                        {
                            "number": "10"
                        }
                    ],
                    "names": [
                        "Cardcaptor Sakura"
                    ]
                },
                "7": {
                    "identifiers": {
                        "anidb": "13060"
                    },
                    "names": [
                        "Cardcaptor Sakura: Clear Card Hen - Prologue - Sakura to Futatsu no Kuma"
                    ],
                    "parameters": {
                        "episode_offset": "6"
                    }
                }
            }
        },
        "1": {
            "identifiers": {
                "anidb": "102"
            },
            "names": [
                "Cardcaptor Sakura"
            ],
            "parameters": {
                "default_season": 1,
                "episode_offset": 0
            }
        },
        "2": {
            "identifiers": {
                "anidb": "102"
            },
            "names": [
                "Cardcaptor Sakura"
            ],
            "parameters": {
                "default_season": 1,
                "episode_offset": 35
            }
        },
        "3": {
            "identifiers": {
                "anidb": "102"
            },
            "names": [
                "Cardcaptor Sakura"
            ],
            "parameters": {
                "default_season": 1,
                "episode_offset": 46
            }
        },
        "4": {
            "identifiers": {
                "anidb": "12140"
            },
            "names": [
                "Cardcaptor Sakura: Clear Card Hen"
            ]
        }
    }
}