{"seasons":{"1":{"identifiers":{"anidb":"2168"},"names":["Major"]},"0":{"episodes":{"3":{"identifiers":{"anidb":"8775"},"mappings":[{"season":"1","number":"1"}],"names":["Major: World Series"]},"2":{"identifiers":{"anidb":"8161"},"mappings":[{"season":"1","number":"1"}],"names":["Major: Message"]},"4":{"identifiers":{"anidb":"8775"},"mappings":[{"season":"1","number":"2"}],"names":["Major: World Series"]}},"identifiers":{"anidb":"5839"},"names":["Gekijouban Major: Yuujou no Winning Shot"]},"3":{"identifiers":{"anidb":"4557"},"names":["Major (2007)"]},"2":{"identifiers":{"anidb":"3423"},"names":["Major (2005)"]},"5":{"identifiers":{"anidb":"6013"},"names":["Major (2009)"]},"4":{"identifiers":{"anidb":"5316"},"names":["Major (2008)"]},"6":{"identifiers":{"anidb":"7236"},"names":["Major (2010)"]}},"identifiers":{"tvdb":"76013"}}