{"33":{"1":{"1":{"1":"715"},"2":["Kidou Senshi Gundam"]},"0":{"49":{"1":{"17":{"1":"729"},"18":["Kidou Senshi Gundam (1981)"],"49":[{"1":"1"},{"1":"1","2":"2"},{"1":"1","2":"3"}]},"3":{"17":{"1":"4167"},"18":["Kidou Senshi Gundam III: Meguriai Sora Hen"],"49":[{"1":"1","2":"1"},{"1":"1","2":"2"},{"1":"1"},{"1":"1","2":"4"},{"1":"1","2":"5"},{"1":"1","2":"6"}]},"2":{"17":{"1":"4166"},"18":["Kidou Senshi Gundam II: Ai Senshi Hen"],"49":[{"1":"1","2":"1"},{"1":"1"},{"1":"1","2":"3"}]},"5":{"49":[{"1":"1","2":"1"},{"1":"1","2":"2"},{"1":"1","2":"3"},{"1":"1","2":"4"},{"1":"1"},{"1":"1","2":"6"}],"18":["Kidou Senshi Gundam F91"],"33":{"1":"Sunrise"},"17":{"1":"626"}},"4":{"49":[{"1":"1","2":"1"},{"1":"1","2":"2"},{"1":"1","2":"3"}],"18":["Kidou Senshi Gundam: Gyakushuu no Char"],"33":{"1":"Sunrise"},"17":{"1":"720"}}}}},"~":1,"1":{"3":"76547"}}