{
    "identifiers": {
        "tvdb": "79525"
    },
    "seasons": {
        "0": {
            "episodes": {
                "1": {
                    "identifiers": {
                        "anidb": "4521"
                    },
                    "mappings": [
                        {
                            "number": "2"
                        }
                    ],
                    "names": [
                        "Code Geass: Hangyaku no Lelouch"
                    ],
                    "supplemental": {
                        "studio": "Sunrise"
                    }
                },
                "10": {
                    "identifiers": {
                        "anidb": "4521"
                    },
                    "mappings": [
                        {
                            "number": "11"
                        }
                    ],
                    "names": [
                        "Code Geass: Hangyaku no Lelouch"
                    ],
                    "supplemental": {
                        "studio": "Sunrise"
                    }
                },
                "11": {
                    "identifiers": {
                        "anidb": "4521"
                    },
                    "mappings": [
                        {
                            "number": "12"
                        }
                    ],
                    "names": [
                        "Code Geass: Hangyaku no Lelouch"
                    ],
                    "supplemental": {
                        "studio": "Sunrise"
                    }
                },
                "12": {
                    "identifiers": {
                        "anidb": "7126"
                    },
                    "mappings": [
                        {
                            "number": "1",
                            "season": "1"
                        }
                    ],
                    "names": [
                        "Code Geass: Hangyaku no Lelouch Special Edition - Black Rebellion"
                    ]
                },
                "13": {
                    "identifiers": {
                        "anidb": "5373"
                    },
                    "mappings": [
                        {
                            "number": "1"
                        }
                    ],
                    "names": [
                        "Code Geass: Hangyaku no Lelouch R2"
                    ],
                    "supplemental": {
                        "studio": "Sunrise"
                    }
                },
                "14": {
                    "identifiers": {
                        "anidb": "5373"
                    },
                    "mappings": [
                        {
                            "number": "2"
                        }
                    ],
                    "names": [
                        "Code Geass: Hangyaku no Lelouch R2"
                    ],
                    "supplemental": {
                        "studio": "Sunrise"
                    }
                },
                "15": {
                    "identifiers": {
                        "anidb": "5373"
                    },
                    "mappings": [
                        {
                            "number": "3"
                        }
                    ],
                    "names": [
                        "Code Geass: Hangyaku no Lelouch R2"
                    ],
                    "supplemental": {
                        "studio": "Sunrise"
                    }
                },
                "16": {
                    "identifiers": {
                        "anidb": "5373"
                    },
                    "mappings": [
                        {
                            "number": "4"
                        }
                    ],
                    "names": [
                        "Code Geass: Hangyaku no Lelouch R2"
                    ],
                    "supplemental": {
                        "studio": "Sunrise"
                    }
                },
                "17": {
                    "identifiers": {
                        "anidb": "5373"
                    },
                    "mappings": [
                        {
                            "number": "5"
                        }
                    ],
                    "names": [
                        "Code Geass: Hangyaku no Lelouch R2"
                    ],
                    "supplemental": {
                        "studio": "Sunrise"
                    }
                },
                "18": {
                    "identifiers": {
                        "anidb": "5373"
                    },
                    "mappings": [
                        {
                            "number": "6"
                        }
                    ],
                    "names": [
                        "Code Geass: Hangyaku no Lelouch R2"
                    ],
                    "supplemental": {
                        "studio": "Sunrise"
                    }
                },
                "19": {
                    "identifiers": {
                        "anidb": "5373"
                    },
                    "mappings": [
                        {
                            "number": "7"
                        }
                    ],
                    "names": [
                        "Code Geass: Hangyaku no Lelouch R2"
                    ],
                    "supplemental": {
                        "studio": "Sunrise"
                    }
                },
                "2": {
                    "identifiers": {
                        "anidb": "4521"
                    },
                    "mappings": [
                        {
                            "number": "4"
                        }
                    ],
                    "names": [
                        "Code Geass: Hangyaku no Lelouch"
                    ],
                    "supplemental": {
                        "studio": "Sunrise"
                    }
                },
                "20": {
                    "identifiers": {
                        "anidb": "5373"
                    },
                    "mappings": [
                        {
                            "number": "8"
                        }
                    ],
                    "names": [
                        "Code Geass: Hangyaku no Lelouch R2"
                    ],
                    "supplemental": {
                        "studio": "Sunrise"
                    }
                },
                "21": {
                    "identifiers": {
                        "anidb": "5373"
                    },
                    "mappings": [
                        {
                            "number": "9"
                        }
                    ],
                    "names": [
                        "Code Geass: Hangyaku no Lelouch R2"
                    ],
                    "supplemental": {
                        "studio": "Sunrise"
                    }
                },
                "22": {
                    "identifiers": {
                        "anidb": "7127"
                    },
                    "mappings": [
                        {
                            "number": "1",
                            "season": "1"
                        }
                    ],
                    "names": [
                        "Code Geass: Hangyaku no Lelouch R2 Special Edition - Zero Requiem"
                    ]
                },
                "23": {
                    "identifiers": {
                        "anidb": "5373"
                    },
                    "mappings": [
                        {
                            "number": "19"
                        }
                    ],
                    "names": [
                        "Code Geass: Hangyaku no Lelouch R2"
                    ],
                    "supplemental": {
                        "studio": "Sunrise"
                    }
                },
                "24": {
                    "identifiers": {
                        "anidb": "8914"
                    },
                    "mappings": [
                        {
                            "number": "1",
                            "season": "1"
                        }
                    ],
                    "names": [
                        "Code Geass: Hangyaku no Lelouch - Nunnally in Wonderland"
                    ]
                },
                "25": {
                    "identifiers": {
                        "anidb": "7508"
                    },
                    "names": [
                        "Code Geass: Boukoku no Akito"
                    ],
                    "parameters": {
                        "episode_offset": "24"
                    }
                },
                "30": {
                    "identifiers": {
                        "anidb": "12567"
                    },
                    "names": [
                        "Gekijou Soushuuhen Code Geass: Hangyaku no Lelouch"
                    ],
                    "parameters": {
                        "episode_offset": "29"
                    }
                },
                "35": {
                    "identifiers": {
                        "anidb": "12566"
                    },
                    "names": [
                        "Code Geass: Fukkatsu no Lelouch"
                    ],
                    "parameters": {
                        "episode_offset": "34"
                    }
                },
                "4": {
                    "identifiers": {
                        "anidb": "4521"
                    },
                    "mappings": [
                        {
                            "number": "5"
                        }
                    ],
                    "names": [
                        "Code Geass: Hangyaku no Lelouch"
                    ],
                    "supplemental": {
                        "studio": "Sunrise"
                    }
                },
                "5": {
                    "identifiers": {
                        "anidb": "4521"
                    },
                    "mappings": [
                        {
                            "number": "6"
                        }
                    ],
                    "names": [
                        "Code Geass: Hangyaku no Lelouch"
                    ],
                    "supplemental": {
                        "studio": "Sunrise"
                    }
                },
                "6": {
                    "identifiers": {
                        "anidb": "4521"
                    },
                    "mappings": [
                        {
                            "number": "7"
                        }
                    ],
                    "names": [
                        "Code Geass: Hangyaku no Lelouch"
                    ],
                    "supplemental": {
                        "studio": "Sunrise"
                    }
                },
                "7": {
                    "identifiers": {
                        "anidb": "4521"
                    },
                    "mappings": [
                        {
                            "number": "8"
                        }
                    ],
                    "names": [
                        "Code Geass: Hangyaku no Lelouch"
                    ],
                    "supplemental": {
                        "studio": "Sunrise"
                    }
                },
                "8": {
                    "identifiers": {
                        "anidb": "4521"
                    },
                    "mappings": [
                        {
                            "number": "9"
                        }
                    ],
                    "names": [
                        "Code Geass: Hangyaku no Lelouch"
                    ],
                    "supplemental": {
                        "studio": "Sunrise"
                    }
                },
                "9": {
                    "identifiers": {
                        "anidb": "4521"
                    },
                    "mappings": [
                        {
                            "number": "10"
                        }
                    ],
                    "names": [
                        "Code Geass: Hangyaku no Lelouch"
                    ],
                    "supplemental": {
                        "studio": "Sunrise"
                    }
                }
            }
        },
        "1": {
            "identifiers": {
                "anidb": "4521"
            },
            "names": [
                "Code Geass: Hangyaku no Lelouch"
            ],
            "supplemental": {
                "studio": "Sunrise"
            }
        },
        "2": {
            "identifiers": {
                "anidb": "5373"
            },
            "names": [
                "Code Geass: Hangyaku no Lelouch R2"
            ],
            "supplemental": {
                "studio": "Sunrise"
            }
        }
    }
}