{"seasons":{"1":{"identifiers":{"anidb":"129"},"names":["Hajime no Ippo: The Fighting!"]},"0":{"episodes":{"3":{"identifiers":{"anidb":"1086"},"parameters":{"episode_offset":"2"},"names":["Hajime no Ippo: The Fighting! - Kimura Tatsuya vs Mashiba Ryo"]}},"identifiers":{"anidb":"982"},"parameters":{"episode_offset":"1"},"names":["Hajime no Ippo: Champion Road"]},"3":{"identifiers":{"anidb":"9982"},"names":["Hajime no Ippo: The Fighting! - Rising"]},"2":{"identifiers":{"anidb":"6153"},"names":["Hajime no Ippo: The Fighting! - New Challenger"]}},"identifiers":{"tvdb":"79685"}}