{"1":{"3":"80096"},"33":{"0":{"1":{"1":"8918"},"2":["Tengen Toppa Gurren Lagann: Ore no Gurren wa Pikka Pika!!"],"49":{"10":{"17":{"1":"6082"},"18":["Gurren Lagann Parallel Works"],"49":[{"1":"1","2":"5"}]},"11":{"17":{"1":"6082"},"18":["Gurren Lagann Parallel Works"],"49":[{"1":"1","2":"6"}]},"12":{"17":{"1":"6082"},"18":["Gurren Lagann Parallel Works"],"49":[{"1":"1","2":"7"}]},"13":{"17":{"1":"6082"},"18":["Gurren Lagann Parallel Works"],"49":[{"1":"1","2":"8"}]},"14":{"17":{"1":"7485"},"18":["Gurren Lagann Parallel Works 2"],"49":[{"1":"1","2":"1"}]},"15":{"17":{"1":"7485"},"18":["Gurren Lagann Parallel Works 2"],"49":[{"1":"1","2":"2"}]},"16":{"17":{"1":"7485"},"18":["Gurren Lagann Parallel Works 2"],"49":[{"1":"1","2":"3"}]},"17":{"17":{"1":"7485"},"18":["Gurren Lagann Parallel Works 2"],"49":[{"1":"1","2":"4"}]},"18":{"17":{"1":"7485"},"18":["Gurren Lagann Parallel Works 2"],"49":[{"1":"1","2":"5"}]},"19":{"17":{"1":"7485"},"18":["Gurren Lagann Parallel Works 2"],"49":[{"1":"1","2":"6"}]},"2":{"17":{"1":"4575"},"18":["Tengen Toppa Gurren Lagann"],"49":[{"2":"1"}]},"20":{"17":{"1":"7485"},"18":["Gurren Lagann Parallel Works 2"],"49":[{"1":"1","2":"7"}]},"21":{"17":{"1":"5783"},"18":["Gekijouban Tengen Toppa Gurren Lagann: Gurren Hen"],"49":[{"2":"1"}]},"22":{"17":{"1":"5783"},"18":["Gekijouban Tengen Toppa Gurren Lagann: Gurren Hen"],"49":[{"2":"2"},{"2":"3"}]},"3":{"17":{"1":"5783"},"18":["Gekijouban Tengen Toppa Gurren Lagann: Gurren Hen"],"49":[{"1":"1","2":"1"}]},"4":{"17":{"1":"6325"},"18":["Gekijouban Tengen Toppa Gurren Lagann: Lagann Hen"],"49":[{"1":"1","2":"1"}]},"5":{"17":{"1":"6609"},"18":["Tengen Toppa Gurren Lagann Kirameki Youko Box: Pieces of Sweet Stars"],"33":{"1":"Gainax"},"49":[{"1":"1","2":"1"}]},"6":{"17":{"1":"6082"},"18":["Gurren Lagann Parallel Works"],"49":[{"1":"1","2":"1"}]},"7":{"17":{"1":"6082"},"18":["Gurren Lagann Parallel Works"],"49":[{"1":"1","2":"2"}]},"8":{"17":{"1":"6082"},"18":["Gurren Lagann Parallel Works"],"49":[{"1":"1","2":"3"}]},"9":{"17":{"1":"6082"},"18":["Gurren Lagann Parallel Works"],"49":[{"1":"1","2":"4"}]}}},"1":{"1":{"1":"4575"},"2":["Tengen Toppa Gurren Lagann"]}},"~":1}