{"33":{"a":{"1":{"1":"69"},"2":["One Piece"]},"0":{"49":{"24":{"17":{"1":"69"},"18":["One Piece"],"49":[{"2":"17"}]},"26":{"17":{"1":"8940"},"18":["One Piece Film: Z"],"49":[{"2":"1"},{"2":"2"}]},"27":{"17":{"1":"8940"},"18":["One Piece Film: Z"],"49":[{"1":"1","2":"1"}]},"20":{"17":{"1":"7538"},"18":["One Piece Film: Strong World - Episode 0"],"49":[{"1":"1","2":"1"}]},"21":{"17":{"1":"8010"},"18":["One Piece 3D: Mugiwara Chase"],"49":[{"1":"1","2":"1"}]},"22":{"17":{"1":"8762"},"18":["One Piece 3D: Gekisou! Trap Coaster"],"49":[{"1":"1","2":"1"}]},"23":{"17":{"1":"69"},"18":["One Piece"],"49":[{"2":"16"}]},"28":{"17":{"1":"69"},"18":["One Piece"],"49":[{"2":"5"}]},"29":{"17":{"1":"69"},"18":["One Piece"],"49":[{"2":"18"}]},"1":{"17":{"1":"2736"},"18":["One Piece: Taose! Kaizoku Ganzack"],"49":[{"1":"1"}]},"3":{"17":{"1":"69"},"18":["One Piece"],"49":[{"2":"1"}]},"2":{"17":{"1":"411"},"18":["One Piece (2000)"],"49":[{"1":"1","2":"1"}]},"5":{"49":[{"2":"1"}],"34":{"2":"3"},"18":["One Piece: Nejimakijima no Bouken"],"17":{"1":"893"}},"7":{"49":[{"2":"1"}],"34":{"2":"5"},"18":["One Piece: Chinjuujima no Chopper Oukoku"],"17":{"1":"1253"}},"9":{"17":{"1":"69"},"18":["One Piece"],"49":[{"2":"2"}]},"8":{"17":{"1":"1254"},"18":["One Piece The Movie: Dead End no Bouken"],"49":[{"1":"1","2":"1"},{"1":"1","2":"2"},{"1":"1","2":"3"}]},"11":{"17":{"1":"2036"},"18":["One Piece: Norowareta Seiken"],"49":[{"1":"1","2":"1"},{"1":"1","2":"2"},{"1":"1","2":"3"}]},"10":{"17":{"1":"69"},"18":["One Piece"],"49":[{"2":"3"}]},"13":{"17":{"1":"2644"},"18":["One Piece: Omatsuri Danshaku to Himitsu no Shima"],"49":[{"1":"1","2":"1"}]},"12":{"17":{"1":"2036"},"18":["One Piece: Norowareta Seiken"],"49":[{"2":"1"}]},"15":{"17":{"1":"4097"},"18":["One Piece The Movie: Karakurijou no Mecha Kyohei"],"49":[{"1":"1","2":"1"}]},"14":{"17":{"1":"69"},"18":["One Piece"],"49":[{"2":"4"}]},"17":{"17":{"1":"5691"},"18":["One Piece The Movie: Episode of Chopper Plus - Fuyu ni Saku, Kiseki no Sakura"],"49":[{"1":"1","2":"1"}]},"16":{"17":{"1":"4851"},"18":["One Piece: Episode of Arabasta - Sabaku no Oujo to Kaizoku-tachi"],"49":[{"1":"1","2":"1"}]},"19":{"17":{"1":"6537"},"18":["One Piece Film: Strong World"],"49":[{"1":"1","2":"1"}]},"32":{"17":{"1":"69"},"18":["One Piece"],"49":[{"2":"22"}]},"31":{"17":{"1":"69"},"18":["One Piece"],"49":[{"2":"21"}]},"30":{"17":{"1":"69"},"18":["One Piece"],"49":[{"2":"19"}]},"18":{"17":{"1":"6199"},"18":["One Piece Special: Romance Dawn Story"],"49":[{"1":"1","2":"1"}]}}}},"~":1,"1":{"3":"81797"}}